python_avatars/__init__.py
python_avatars/__main__.py
python_avatars/accessory_types.py
python_avatars/avatar.py
python_avatars/avatar_styles.py
python_avatars/background_colors.py
python_avatars/base_enums.py
python_avatars/clothing_colors.py
python_avatars/clothing_graphics.py
python_avatars/clothing_types.py
python_avatars/core.py
python_avatars/default.json
python_avatars/eye_types.py
python_avatars/eyebrow_types.py
python_avatars/facial_hair_types.py
python_avatars/hair_colors.py
python_avatars/hair_types.py
python_avatars/hat_types.py
python_avatars/mouth_types.py
python_avatars/nose_types.py
python_avatars/skin_colors.py
python_avatars/svg_parser.py
python_avatars/top_types.py
python_avatars/avatar_parts/accessories/eyepatch.svg
python_avatars/avatar_parts/accessories/kurt.svg
python_avatars/avatar_parts/accessories/prescription_01.svg
python_avatars/avatar_parts/accessories/prescription_02.svg
python_avatars/avatar_parts/accessories/round.svg
python_avatars/avatar_parts/accessories/sunglasses.svg
python_avatars/avatar_parts/accessories/sunglasses_2.svg
python_avatars/avatar_parts/accessories/wayfarers.svg
python_avatars/avatar_parts/accessories/wayfarers_2.svg
python_avatars/avatar_parts/clothes/astronaut_suit.svg
python_avatars/avatar_parts/clothes/blazer_shirt.svg
python_avatars/avatar_parts/clothes/blazer_sweater.svg
python_avatars/avatar_parts/clothes/bond_suit.svg
python_avatars/avatar_parts/clothes/chef.svg
python_avatars/avatar_parts/clothes/collar_sweater.svg
python_avatars/avatar_parts/clothes/gladiator.svg
python_avatars/avatar_parts/clothes/graphic_shirt.svg
python_avatars/avatar_parts/clothes/hoodie.svg
python_avatars/avatar_parts/clothes/jedi_robe.svg
python_avatars/avatar_parts/clothes/overall.svg
python_avatars/avatar_parts/clothes/shirt_crew_neck.svg
python_avatars/avatar_parts/clothes/shirt_scoop_neck.svg
python_avatars/avatar_parts/clothes/shirt_v_neck.svg
python_avatars/avatar_parts/clothes/shirt_wick.svg
python_avatars-1.4.1.dist-info/LICENSE
python_avatars-1.4.1.dist-info/METADATA
python_avatars-1.4.1.dist-info/WHEEL
python_avatars-1.4.1.dist-info/top_level.txt
python_avatars-1.4.1.dist-info/RECORD
