Metadata-Version: 2.1
Name: python_avatars
Version: 1.4.1
Summary: SVG avatar library for Python
Home-page: https://github.com/ibonn/python_avatars
Download-URL: https://pypi.org/project/python_avatars/
Author: Ibon
Author-email: ibonescartin@gmail.com
License: MIT
Project-URL: Documentation, https://readthedocs.org/projects/python_avatars/
Project-URL: Source Code, https://github.com/ibonn/python_avatars
Keywords: avatar,svg,python,face,custom
Classifier: Development Status :: 5 - Production/Stable
Classifier: Intended Audience :: Developers
Classifier: License :: OSI Approved :: MIT License
Classifier: Operating System :: OS Independent
Classifier: Programming Language :: Python
Classifier: Programming Language :: Python :: 3
Classifier: Topic :: Multimedia
Classifier: Topic :: Multimedia :: Graphics
Classifier: Topic :: Software Development :: Libraries :: Python Modules
License-File: LICENSE
